yedextended/__init__.py
yedextended-2.0.1.dist-info/licenses/LICENSE
yedextended-2.0.1.dist-info/METADATA
yedextended-2.0.1.dist-info/WHEEL
yedextended-2.0.1.dist-info/top_level.txt
yedextended-2.0.1.dist-info/RECORD
