Metadata-Version: 2.4
Name: yedextended
Version: 2.0.1
Summary: Python library extending yEd functionality through programmatic interface to graphs.
Author-email: Cole St John <info@colestjohn.com>
Project-URL: Homepage, https://github.com/cole-st-john/yedextended
Project-URL: Issues, https://github.com/cole-st-john/yedextended/issues
Classifier: Programming Language :: Python :: 3 :: Only
Classifier: Programming Language :: Python :: 3.10
Classifier: Programming Language :: Python :: 3.11
Classifier: Programming Language :: Python :: 3.12
Classifier: License :: OSI Approved :: BSD License
Classifier: Operating System :: OS Independent
Requires-Python: >=3.10
License-File: LICENSE
Requires-Dist: openpyxl>=3.1.5
Requires-Dist: pandas>=2.2.3
Requires-Dist: psutil>=6.1.0
Dynamic: license-file
